rctclient/__init__.py
rctclient/cli.py
rctclient/exceptions.py
rctclient/frame.py
rctclient/py.typed
rctclient/registry.py
rctclient/simulator.py
rctclient/types.py
rctclient/utils.py
rctclient-0.0.4.dist-info/licenses/LICENSE.txt
rctclient-0.0.4.dist-info/METADATA
rctclient-0.0.4.dist-info/WHEEL
rctclient-0.0.4.dist-info/entry_points.txt
rctclient-0.0.4.dist-info/top_level.txt
rctclient-0.0.4.dist-info/RECORD
