Metadata-Version: 2.4
Name: rctclient
Version: 0.0.4
Summary: Implementation of the RCT Power communication protocol
Home-page: https://github.com/svalouch/python-rctclient/
Author: Stefan Valouch
Author-email: svalouch@valouch.com
Project-URL: Documentation, https://rctclient.readthedocs.io/
Project-URL: Source, https://github.com/svalouch/python-rctclient/
Project-URL: Tracker, https://github.com/svalouch/python-rctclient/issues
Platform: any
Classifier: Development Status :: 2 - Pre-Alpha
Classifier: License :: OSI Approved :: GNU General Public License v3 (GPLv3)
Classifier: Operating System :: OS Independent
Classifier: Programming Language :: Python
Classifier: Programming Language :: Python :: 3
Classifier: Programming Language :: Python :: 3 :: Only
Classifier: Programming Language :: Python :: 3.6
Classifier: Programming Language :: Python :: 3.7
Classifier: Programming Language :: Python :: 3.8
Classifier: Programming Language :: Python :: 3.9
Classifier: Programming Language :: Python :: 3.10
Classifier: Programming Language :: Python :: 3.11
Requires-Python: >=3.6
License-File: LICENSE.txt
Requires-Dist: typing_extensions; python_version < "3.8"
Provides-Extra: cli
Requires-Dist: click<8.2,>=7.0; extra == "cli"
Provides-Extra: tests
Requires-Dist: mypy; extra == "tests"
Requires-Dist: pylint; extra == "tests"
Requires-Dist: pytest; extra == "tests"
Requires-Dist: pytest-cov; extra == "tests"
Requires-Dist: pytest-pylint; extra == "tests"
Provides-Extra: docs
Requires-Dist: click<8.2,>=7.0; extra == "docs"
Requires-Dist: Sphinx>=2.0; extra == "docs"
Requires-Dist: sphinx-autodoc-typehints; extra == "docs"
Requires-Dist: sphinx-click; extra == "docs"
Requires-Dist: sphinx-rtd-theme; extra == "docs"
Requires-Dist: recommonmark>=0.5.0; extra == "docs"
Dynamic: author
Dynamic: author-email
Dynamic: classifier
Dynamic: description
Dynamic: description-content-type
Dynamic: home-page
Dynamic: license-file
Dynamic: platform
Dynamic: project-url
Dynamic: provides-extra
Dynamic: requires-dist
Dynamic: requires-python
Dynamic: summary
